mongodantic/__init__.py
mongodantic/conftest.py
mongodantic/model.py
mongodantic/test_mongodantic.py
mongodantic_python-0.5.0.dist-info/LICENSE.md
mongodantic_python-0.5.0.dist-info/METADATA
mongodantic_python-0.5.0.dist-info/WHEEL
mongodantic_python-0.5.0.dist-info/RECORD
