Metadata-Version: 2.1
Name: mongodantic-python
Version: 0.5.0
Summary: Pydantic models for MongoDB
Home-page: https://github.com/cocreators-ee/mongodantic/
License: BSD-3-Clause
Keywords: database,mongodb,pymongo,odm,async
Author: Janne Enberg
Author-email: janne.enberg@lietu.net
Requires-Python: >=3.8,<4
Classifier: License :: OSI Approved :: BSD License
Classifier: Programming Language :: Python :: 3
Classifier: Programming Language :: Python :: 3.8
Classifier: Programming Language :: Python :: 3.9
Classifier: Programming Language :: Python :: 3.10
Classifier: Programming Language :: Python :: 3.11
Classifier: Programming Language :: Python :: 3.12
Requires-Dist: motor (>=3.1.1,<4.0.0)
Requires-Dist: pydantic (>=2.0.0)
Requires-Dist: pymongo (>=4.7.3,<5.0.0)
Project-URL: Documentation, https://github.com/cocreators-ee/mongodantic/
Project-URL: Repository, https://github.com/cocreators-ee/mongodantic/
